datatrees/__init__.py
datatrees/datatrees.py
datatrees-0.3.7.dist-info/METADATA
datatrees-0.3.7.dist-info/WHEEL
datatrees-0.3.7.dist-info/licenses/LICENSE
datatrees-0.3.7.dist-info/RECORD
