Metadata-Version: 2.4
Name: datatrees
Version: 0.3.7
Summary: Wrapper for dataclasses with auto field injection, binding, self-default lamdas and more.
Project-URL: Homepage, https://github.com/owebeeone/datatrees
Project-URL: Bug Tracker, https://github.com/owebeeone/datatrees/issues
Author-email: Gianni Mariani <gianni@mariani.ws>
License-File: LICENSE
Classifier: License :: OSI Approved :: GNU Lesser General Public License v2 or later (LGPLv2+)
Classifier: Operating System :: OS Independent
Classifier: Programming Language :: Python :: 3
Requires-Python: >=3.10
Requires-Dist: frozendict>=2.3.8
Requires-Dist: sortedcollections>=2.1.0
Provides-Extra: types
Requires-Dist: typing-extensions>=4.1.0; (python_version < '3.11') and extra == 'types'
